[
    {
        "id": "95c6201c-c73d-4255-a110-909df95f9b83",
        "category_id": "062960f8-933e-492a-8a01-7181361b0f3d",
        "employee_id": "b84f66a6-7134-438e-8123-f27fe78f35ec",
        "name": "Apple MacBook Pro 14” M1 Pro 16GB 1TB (MKGT3ZE/A)",
        "description": "I was using an Intel-based 13” MacBook Pro prior to this and the difference is night and day. I’ve never heard the fans turn on a single time, even under the incredibly heavy loads I put it through with our various launch simulations.",
        "link": false,
        "link_label": "",
        "link_url": "",
        "created_at": "2023-01-05T11:39:48.436Z",
        "updated_at": "2023-01-05T11:39:48.436Z"
    },
    {
        "id": "04ba706c-cb6d-44fd-bc8b-b45240ebce2e",
        "category_id": "062960f8-933e-492a-8a01-7181361b0f3d",
        "employee_id": "b84f66a6-7134-438e-8123-f27fe78f35ec",
        "name": "Apple Magic Trackpad",
        "description": "Magic Trackpad is wireless and rechargeable, and it includes the full range of Multi-Touch gestures and Force Touch technology. Magic Trackpad pairs automatically with your Mac, so you can get to work right away. The rechargeable battery will power it for about a month or more between charges.",
        "link": false,
        "link_label": "",
        "link_url": "",
        "created_at": "2023-01-05T11:39:48.436Z",
        "updated_at": "2023-01-05T11:39:48.436Z"
    },
    {
        "id": "771f89cf-cedc-411b-8c0c-0b7dab3f6433",
        "category_id": "71700072-267e-47a6-bb41-a8b341c48686",
        "employee_id": "b84f66a6-7134-438e-8123-f27fe78f35ec",
        "name": "Native macOS Terminal",
        "description": "",
        "link": false,
        "link_label": "",
        "link_url": "",
        "created_at": "2023-01-05T11:39:48.436Z",
        "updated_at": "2023-01-05T11:39:48.436Z"
    },
    {
        "id": "fd20d6a8-a7f6-4e77-9cdc-972d09a9d8d4",
        "category_id": "062960f8-933e-492a-8a01-7181361b0f3d",
        "employee_id": "b84f66a6-7134-438e-8123-f27fe78f35ec",
        "name": "Magic Keyboard with Numeric Keypad",
        "description": "Magic Keyboard with Numeric Keypad features an extended layout, with document navigation controls for quick scrolling and full-size arrow keys. And the built-in, rechargeable battery is incredibly long-lasting, powering your keyboard for about a month or more between charges",
        "link": false,
        "link_label": "",
        "link_url": "",
        "created_at": "2023-01-05T11:39:48.436Z",
        "updated_at": "2023-01-05T11:39:48.436Z"
    },
    {
        "id": "5f92922c-2c3d-4d9d-bb5d-bf0a928a3637",
        "category_id": "71700072-267e-47a6-bb41-a8b341c48686",
        "employee_id": "b84f66a6-7134-438e-8123-f27fe78f35ec",
        "name": "Visual Studio Code",
        "description": "Visual Studio Code is a lightweight but powerful source code editor",
        "link": true,
        "link_label": "www.code.visualstudio.com",
        "link_url": "https://code.visualstudio.com",
        "created_at": "2023-01-05T11:39:48.436Z",
        "updated_at": "2023-01-05T11:39:48.436Z"
    },
    {
        "id": "20af28cd-6310-4ec5-a23b-4b3b075577c3",
        "category_id": "71700072-267e-47a6-bb41-a8b341c48686",
        "employee_id": "b84f66a6-7134-438e-8123-f27fe78f35ec",
        "name": "Supabase",
        "description": "Supabase is an open source Firebase alternative",
        "link": true,
        "link_label": "www.supabase.com",
        "link_url": "https://supabase.com",
        "created_at": "2023-01-05T11:39:48.436Z",
        "updated_at": "2023-01-05T11:39:48.436Z"
    },
    {
        "id": "3f1a67bf-1d20-403d-a42f-7c061d039b94",
        "category_id": "71700072-267e-47a6-bb41-a8b341c48686",
        "employee_id": "b84f66a6-7134-438e-8123-f27fe78f35ec",
        "name": "Vercel",
        "description": "Vercel is the platform for frontend developers, providing the speed and reliability innovators need to create at the moment of inspiration.",
        "link": true,
        "link_label": "www.vercel.com",
        "link_url": "https://vercel.com",
        "created_at": "2023-01-05T11:39:48.436Z",
        "updated_at": "2023-01-05T11:39:48.436Z"
    },
    {
        "id": "101ee9ec-1ca0-4d16-874d-66bc858a5f12",
        "category_id": "71700072-267e-47a6-bb41-a8b341c48686",
        "employee_id": "b84f66a6-7134-438e-8123-f27fe78f35ec",
        "name": "Uploadcare",
        "description": "Power up file uploading, processing and delivery for your app in one sitting.",
        "link": true,
        "link_label": "www.uploadcare.com",
        "link_url": "https://uploadcare.com",
        "created_at": "2023-01-05T11:39:48.436Z",
        "updated_at": "2023-01-05T11:39:48.436Z"
    },
    {
        "id": "9b93bcbd-e508-4930-be28-77fd3931d924",
        "category_id": "71700072-267e-47a6-bb41-a8b341c48686",
        "employee_id": "b84f66a6-7134-438e-8123-f27fe78f35ec",
        "name": "Dhosting",
        "description": "The simplicity and intuitiveness of the administration panel, as well as the possibility of editing many elements from its level.",
        "link": true,
        "link_label": "www.dhosting.pl",
        "link_url": "https://dhosting.pl",
        "created_at": "2023-01-05T11:39:48.436Z",
        "updated_at": "2023-01-05T11:39:48.436Z"
    },
    {
        "id": "855adc90-5c11-4fdf-9baf-204d61ae97af",
        "category_id": "71700072-267e-47a6-bb41-a8b341c48686",
        "employee_id": "b84f66a6-7134-438e-8123-f27fe78f35ec",
        "name": "SVGO",
        "description": "Node.js tool for optimizing SVG files",
        "link": true,
        "link_label": "www.github.com/svg/svgo",
        "link_url": "https://github.com/svg/svgo",
        "created_at": "2023-01-05T11:39:48.436Z",
        "updated_at": "2023-01-05T11:39:48.436Z"
    },
    {
        "id": "d156c709-83ab-4c64-ba61-98a1cfbead79",
        "category_id": "c83b6c11-d430-46a8-bccf-facb96edb281",
        "employee_id": "b84f66a6-7134-438e-8123-f27fe78f35ec",
        "name": "Sketch",
        "description": "Sketch gives you all the tools you need for a truly collaborative design process. From early ideas to pixel-perfect artwork, playable prototypes and developer handoff.",
        "link": true,
        "link_label": "www.sketch.com",
        "link_url": "https://sketch.com",
        "created_at": "2023-01-05T11:39:48.436Z",
        "updated_at": "2023-01-05T11:39:48.436Z"
    },
    {
        "id": "2d534c4e-2655-4d29-84bf-24bfb8b872fb",
        "category_id": "55575323-ee19-4d66-a39f-fc9a7b388d06",
        "employee_id": "b84f66a6-7134-438e-8123-f27fe78f35ec",
        "name": "Focus on Mac",
        "description": "When you need to stay on task and minimize distractions, use Focus. You can use a Focus to pause and silence all notifications or allow only certain notifications—for example, ones from colleagues on an urgent project. You can also share that you’ve silenced notifications so contacts know you’re busy.",
        "link": false,
        "link_label": "",
        "link_url": "",
        "created_at": "2023-01-05T11:39:48.436Z",
        "updated_at": "2023-01-05T11:39:48.436Z"
    },
    {
        "id": "12365cc6-bba0-4b4a-a9de-cea3f343aae7",
        "category_id": "71700072-267e-47a6-bb41-a8b341c48686",
        "employee_id": "b84f66a6-7134-438e-8123-f27fe78f35ec",
        "name": "Railway",
        "description": "Railway is a deployment platform where you can provision infrastructure, develop with that infrastructure locally, and then deploy to the cloud.",
        "link": true,
        "link_label": "www.railway.app",
        "link_url": "https://railway.app",
        "created_at": "2023-01-05T11:39:48.436Z",
        "updated_at": "2023-01-05T11:39:48.436Z"
    },
    {
        "id": "bd4ae136-7ee7-4071-8ef8-93e751532888",
        "category_id": "55575323-ee19-4d66-a39f-fc9a7b388d06",
        "employee_id": "b84f66a6-7134-438e-8123-f27fe78f35ec",
        "name": "Everhour",
        "description": "Free time tracking software with hassle-free integrations",
        "link": true,
        "link_label": "www.everhour.com",
        "link_url": "https://everhour.com",
        "created_at": "2023-01-15T19:01:31.362Z",
        "updated_at": "2023-01-15T19:01:31.362Z"
    },
    {
        "id": "932a7747-78d7-43ea-b689-0fc3f79c6ebc",
        "category_id": "55575323-ee19-4d66-a39f-fc9a7b388d06",
        "employee_id": "b84f66a6-7134-438e-8123-f27fe78f35ec",
        "name": "Rectangle",
        "description": "Move and resize windows in macOS using keyboard shortcuts or snap areas",
        "link": false,
        "link_label": "www.rectangleapp.com",
        "link_url": "https://rectangleapp.com",
        "created_at": "2023-01-15T19:07:09.459Z",
        "updated_at": "2023-01-15T19:07:09.459Z"
    },
    {
        "id": "9cb59bf4-3df9-402b-8870-295d0f1d3a5f",
        "category_id": "55575323-ee19-4d66-a39f-fc9a7b388d06",
        "employee_id": "b84f66a6-7134-438e-8123-f27fe78f35ec",
        "name": "Meeting Bar",
        "description": "Your next meeting always before your eyes in the macOS menu bar",
        "link": true,
        "link_label": "www.brew.sh/meetingbar",
        "link_url": "https://formulae.brew.sh/cask/meetingbar#default",
        "created_at": "2023-01-15T19:38:14.262Z",
        "updated_at": "2023-01-15T19:38:14.262Z"
    }
]